Prac5/Code/adc.v
// TSC simulation module

// set simulation time:
`timescale 1ns / 1ps

module ADC (
    input wire req,      // Request signal from TSC
    input wire rst,      // Reset signal for ADC
    output reg rdy,      // Ready signal to indicate completion
    output reg [7:0] dat // Data output from the array
);

// Constant array of values (16 data values)
  // reg [7:0]
  // integer adc_data [15:0] = {
  reg [0:7] adc_data [0:40];
    
  initial
    begin 
      // hard-coded ADC values stored in adc_data
      // it seams iVerilog doesn't want to initialize an array
      // adc_data[ 0] = 8'h8B;
      // adc_data[ 1] = 8'h8C;
      // adc_data[ 2] = 8'h99;
      // adc_data[ 3] = 8'h9B;
      // adc_data[ 4] = 8'h93;
      // adc_data[ 5] = 8'h82;
      // adc_data[ 6] = 8'h97;
      // adc_data[ 7] = 8'h90;
      // adc_data[ 8] = 8'h9F;
      // adc_data[ 9] = 8'hD7;
      // adc_data[10] = 8'h8D;
      // adc_data[11] = 8'h9C;
      // adc_data[12] = 8'h85;
      // adc_data[13] = 8'h8A;
      // adc_data[14] = 8'h91;
      // adc_data[15] = 8'h8C;

      // OVERFLOW TEST
      // adc_data[ 0] = 8'h8B;
      // adc_data[ 1] = 8'h8C;
      // adc_data[ 2] = 8'h99;
      // adc_data[ 3] = 8'h9B;
      // adc_data[ 4] = 8'h93;
      // adc_data[ 5] = 8'h82;
      // adc_data[ 6] = 8'h97;
      // adc_data[ 7] = 8'h90;
      // adc_data[ 8] = 8'h9F;
      // adc_data[ 9] = 8'h93;
      // adc_data[10] = 8'hD6;
      // adc_data[11] = 8'h9C;
      // adc_data[12] = 8'h85;
      // adc_data[13] = 8'h8A;
      // adc_data[14] = 8'h91;
      // adc_data[15] = 8'h8C;
      // adc_data[16] = 8'h81;
      // adc_data[17] = 8'h8B;
      // adc_data[18] = 8'h99;
      // adc_data[19] = 8'h9B;
      // adc_data[20] = 8'h93;
      // adc_data[21] = 8'h82;
      // adc_data[22] = 8'h97;
      // adc_data[23] = 8'h90;
      // adc_data[24] = 8'h9F;
      // adc_data[25] = 8'hA7;
      // adc_data[26] = 8'h8D;
      // adc_data[27] = 8'h9C;
      // adc_data[28] = 8'h85;
      // adc_data[29] = 8'h8A;
      // adc_data[30] = 8'h91;
      // adc_data[31] = 8'h8C;
      // adc_data[32] = 8'hD6;
      // adc_data[33] = 8'h81;
      // adc_data[34] = 8'h8B;
      // adc_data[35] = 8'h99;
      // adc_data[36] = 8'h9B;
      // adc_data[37] = 8'h93;
      // adc_data[38] = 8'h82;
      // adc_data[39] = 8'h97;
      // adc_data[40] = 8'h86;

      // Test values close to trigger value
      adc_data[ 0] = 8'hD4; // 212
      adc_data[ 1] = 8'hD4; // 212
      adc_data[ 2] = 8'hD3; // 211
      adc_data[ 3] = 8'hD2; // 210
      adc_data[ 4] = 8'h88; // 
      adc_data[ 5] = 8'hD4; // 212
      adc_data[ 6] = 8'hD4; // 212
      adc_data[ 7] = 8'hD4; // 212
      adc_data[ 8] = 8'hD4; // 212
      adc_data[ 9] = 8'hD4; // 212
      adc_data[10] = 8'hD4; // 212
      adc_data[11] = 8'hD4; // 212
      adc_data[12] = 8'hD4; // 212
      adc_data[13] = 8'hD4; // 212
      adc_data[14] = 8'hD4; // 212
      adc_data[15] = 8'hD4; // 212
      adc_data[16] = 8'hD4; // 212
      adc_data[17] = 8'hD4; // 212
      adc_data[18] = 8'hD4; // 212
      adc_data[19] = 8'hD4; // 212
      adc_data[20] = 8'hD4; // 212
      adc_data[21] = 8'hD4; // 212
      adc_data[22] = 8'hD4; // 212
      adc_data[23] = 8'hD4; // 212
      adc_data[24] = 8'hD5; // 213
      adc_data[25] = 8'hD3; // 211
      adc_data[26] = 8'hD3; // 211
      adc_data[27] = 8'hD3; // 211
      adc_data[28] = 8'hD3; // 211
      adc_data[29] = 8'hD3; // 211
      adc_data[30] = 8'hD3; // 211
      adc_data[31] = 8'hD6; // 214
      adc_data[32] = 8'hD3; // 211
      adc_data[33] = 8'hD3; // 211
      adc_data[34] = 8'hD3; // 211
      adc_data[35] = 8'hD3; // 211
      adc_data[36] = 8'hD3; // 211
      adc_data[37] = 8'hD3; // 211
      adc_data[38] = 8'hD3; // 211
      adc_data[39] = 8'hD3; // 211
      adc_data[40] = 8'hD3; // 211

    end
  
  
  reg [7:0] idx = 0; // Index to access the array
  

always @(posedge req or posedge rst) begin
    if (rst) begin
        // Reset the device
        rdy <= 0;
        dat <= 8'b00000000; // Reset data output
        idx <= 0; // Reset array index
    end else if (req) begin
        // Read data from the sample array using modular arithmetic
        dat <= adc_data[idx % 41]; // Wrap around if idx exceeds 15
        idx <= idx + 1;

        // Raise RDY line
        rdy <= 1;
    end else begin
        // Lower RDY line if not processing
        rdy <= 0;
    end
end

endmodule

Prac5/Code/tsc.v
`timescale 1ns / 1ps

module TSC (
    input wire rst,
    input wire start,
    input wire clk,
    input wire [7:0] adc_data,
    input wire rdy,
    input wire sbf,
    output reg trd,
    output reg cd,
    // output reg [31:0] trigtm,
    output reg req,
    output reg [8:0] sd
    // output reg [31:0] timer
);

    // Instantiate ADC module
    ADC adc_inst (
        .req(req),
        .rst(rst),
        .rdy(rdy),
        .dat(adc_data)
    );

    // State definitions
    localparam IDLE         = 4'b0000;
    localparam RUNNING      = 4'b0001;
    localparam TRIGGERED    = 4'b0010;
    localparam BUFFER_SEND  = 4'b0011;

    // Constants
    localparam BUFFER_SIZE = 32;
    localparam TRIGVL = 8'b11010101; // Trigger value

    // Registers
    reg [3:0] state;
    reg [4:0] head, tail;
    reg [7:0] ring_buffer [0:BUFFER_SIZE-1];
    reg [4:0] captured_no;
    reg [7:0] i, temp;
    reg [31:0] timer;
    reg timer_increment_flag;
    output reg [31:0] trigtm;

    always @ (posedge clk or posedge rst) begin
        if (rst) begin
            // Reset values
            state <= IDLE;
            timer <= 32'h0;
            head <= 5'b0;
            tail <= 5'b0;
            trd <= 1'b0;
            cd <= 1'b1;
            sd <= 1'b0;
            captured_no <= 0;
            trigtm <= 32'h0;
            req <= 1'b0;
            i <= 8'h0;
            timer_increment_flag <= 1'b0;
            $display("TSC Reset.");
        end else begin
            // Increments timer if not in IDLE or SEND_BUFFER state
            if (timer_increment_flag) begin
                timer <= timer + 1;
            end
            // State machine
            case (state)
                IDLE: begin
                    $display("state: IDLE, sbf = %b, trd = %b", sbf, trd);
                    if (start) begin
                        trigtm <= 32'h0;
                        state <= RUNNING;
                        req <= 1'b1;
                        timer_increment_flag <= 1'b1; // Start timer
                        $display("Start received");
                    end else if (sbf && trd) begin
                        $display("Entering Buffer Send mode");
                        state <= BUFFER_SEND;
                        sd <= 1'b1;
                        cd <= 1'b0;
                    end
                end
                RUNNING: begin
                    $display("state: RUNNING.");
                    req <= 1'b1;
                    if (adc_data < TRIGVL) begin
                        if (req && rdy) begin
                            // $display("data=%d", adc_data);
                            ring_buffer[head] <= adc_data;
                            head <= (head + 1) % BUFFER_SIZE;
                            // timer <= timer + 1;
                            req <= 1'b0;
                        end
                    end else begin
                        temp <= timer;
                        state <= TRIGGERED;
                        $display("Triggered, data=%d",adc_data);
                    end
                end
                TRIGGERED: begin
                    req <= 1'b1;
                    trigtm <= temp + 1;
                    if (req && rdy) begin
                        ring_buffer[head] <= adc_data;
                        head <= (head + 1) % BUFFER_SIZE;
                        captured_no <= captured_no + 1;
                        req <= 1'b0;
                        if (captured_no == 16) begin
                            trd <= 1'b1; // pull trigger detected line high
                            req <= 1'b0; // stop adc value request
                            timer_increment_flag <= 1'b0; // stop timer
                            state <= IDLE;
                        end else begin
                            // timer <= timer + 1;
                            req <= 1'b0; // Make sure tsc isn't requesting readings from adc
                        end
                    end
                end
                BUFFER_SEND: begin
                    if (i < 32) begin
                        sd <= {1'b0, ring_buffer[tail]};
                        tail <= (tail + 1) % BUFFER_SIZE;
                        i <= i + 1;
                    end else begin
                        $display("Buffer send complete from tsc side.");
                        trd <= 1'b0;
                        sd <= 1'b0;
                        cd <= 1'b1;
                        state <= IDLE;
                    end
                end
            endcase
        end
    end

endmodule

Prac5/Code/tsc_tb.v
// TSC Test Bench

module tsc_tb;

    // Var declaration
    integer count;

    // Parameters
    parameter CLK_PERIOD = 10; // Clock period in ns

    // Signals
    reg rst, start, clk, sbf;
    wire trd, cd;
    wire [8:0] sd;

    // Instantiate the TSC module
    TSC tsc_inst (
        .rst(rst),
        .start(start),
        .clk(clk),
        .sbf(sbf),
        .trd(trd),
        .sd(sd),
        .cd(cd)
    );

    // Clock generation
    // always #((CLK_PERIOD)/2) clk = ~clk;

    initial begin
        // 100ns clock period
        clk = 1'b0;
        forever #50 clk = ~clk;
    end

    initial begin
        $dumpfile("trigger_test.vcd");
        $dumpvars(0,tsc_tb);
    end


    // Stimulus
    initial begin
        // Push reset line high to reset TSC module
        rst = 1; 
        start = 0; 

        #20 rst = 0; // Deassert reset

        // Start the TSC by pushing the start line high
        #100 start = 1;
        #100 start = 0;

        // Wait until the tigger is detected
        @(posedge trd);
        $display("Test Bench captured trigger event.");
        
        // Checks if the current timer value is stored in the TRIGTM register on a trigger event
        if (tsc_inst.trigtm == 0) begin
            $display("ERROR: TRIGTM not captured");
        end else begin
            $display("TRIGTM: %d", tsc_inst.trigtm);
        end

        // Send buffer request
        #100 sbf = 1;
        @(posedge sd);
        sbf = 0;

        // @(posedge sd);

        // Print the data being sent on the SD line for 32 bytes,
        // if done correctly, a new value should be sent every 
        // positive clock cycle, so this should print out 32
        // 'different' values.
        for (count = 0; count < 32; count = count +1)
        begin 
            @(posedge clk);
            $display("SD Data: %b", {sd[8], sd[7:0]});
            $display("SD Data (in decimal): %d", sd);
        end

        // Wait for the data to finish sending
        @(posedge cd);
        $display("Test bench received buffer send completed");

        // Display the data sent in sd
        // $display("SD Data: %b", {sd[8], sd[7:0]});

        #2000 $finish;
    end

endmodule

Prac5/Code/buffer_under.vcd
$date
	Fri May  3 09:19:33 2024
$end
$version
	Icarus Verilog
$end
$timescale
	1ps
$end
$scope module tsc_tb $end
$var wire 1 ! trd $end
$var wire 9 " sd [8:0] $end
$var wire 1 # cd $end
$var parameter 32 $ CLK_PERIOD $end
$var reg 1 % clk $end
$var reg 1 & rst $end
$var reg 1 ' sbf $end
$var reg 1 ( start $end
$var integer 32 ) count [31:0] $end
$scope module tsc_inst $end
$var wire 1 % clk $end
$var wire 1 & rst $end
$var wire 1 ' sbf $end
$var wire 1 ( start $end
$var wire 1 * rdy $end
$var wire 8 + adc_data [7:0] $end
$var parameter 4 , BUFFER_SEND $end
$var parameter 32 - BUFFER_SIZE $end
$var parameter 4 . IDLE $end
$var parameter 4 / RUNNING $end
$var parameter 4 0 TRIGGERED $end
$var parameter 8 1 TRIGVL $end
$var reg 5 2 captured_no [4:0] $end
$var reg 1 # cd $end
$var reg 5 3 head [4:0] $end
$var reg 8 4 i [7:0] $end
$var reg 1 5 req $end
$var reg 9 6 sd [8:0] $end
$var reg 4 7 state [3:0] $end
$var reg 5 8 tail [4:0] $end
$var reg 8 9 temp [7:0] $end
$var reg 32 : timer [31:0] $end
$var reg 1 ; timer_increment_flag $end
$var reg 1 ! trd $end
$var reg 32 < trigtm [31:0] $end
$scope module adc_inst $end
$var wire 1 5 req $end
$var wire 1 & rst $end
$var reg 8 = dat [7:0] $end
$var reg 8 > idx [7:0] $end
$var reg 1 * rdy $end
$upscope $end
$upscope $end
$upscope $end
$enddefinitions $end
$comment Show the parameter values. $end
$dumpall
b11010101 1
b10 0
b1 /
b0 .
b100000 -
b11 ,
b1010 $
$end
#0
$dumpvars
b0 >
b0 =
b0 <
0;
b0 :
bx 9
b0 8
b0 7
b0 6
05
b0 4
b0 3
b0 2
b0 +
0*
bx )
0(
x'
1&
0%
1#
b0 "
0!
$end
#20000
0&
#50000
1%
#100000
0%
#120000
1(
#150000
1*
b1 >
b10001011 +
b10001011 =
1;
15
b1 7
1%
#200000
0%
#220000
0(
#250000
05
b1 3
b1 :
1%
#300000
0%
#350000
b10 >
b10001100 +
b10001100 =
15
b10 :
1%
#400000
0%
#450000
05
b10 3
b11 :
1%
#500000
0%
#550000
b11 >
b10011001 +
b10011001 =
15
b100 :
1%
#600000
0%
#650000
05
b11 3
b101 :
1%
#700000
0%
#750000
b100 >
b10011011 +
b10011011 =
15
b110 :
1%
#800000
0%
#850000
05
b100 3
b111 :
1%
#900000
0%
#950000
b101 >
b10010011 +
b10010011 =
15
b1000 :
1%
#1000000
0%
#1050000
05
b101 3
b1001 :
1%
#1100000
0%
#1150000
b110 >
b10000010 +
b10000010 =
15
b1010 :
1%
#1200000
0%
#1250000
05
b110 3
b1011 :
1%
#1300000
0%
#1350000
b111 >
b10010111 +
b10010111 =
15
b1100 :
1%
#1400000
0%
#1450000
05
b111 3
b1101 :
1%
#1500000
0%
#1550000
b1000 >
b10010000 +
b10010000 =
15
b1110 :
1%
#1600000
0%
#1650000
05
b1000 3
b1111 :
1%
#1700000
0%
#1750000
b1001 >
b10011111 +
b10011111 =
15
b10000 :
1%
#1800000
0%
#1850000
05
b1001 3
b10001 :
1%
#1900000
0%
#1950000
b1010 >
b10010011 +
b10010011 =
15
b10010 :
1%
#2000000
0%
#2050000
05
b1010 3
b10011 :
1%
#2100000
0%
#2150000
b1011 >
b11010110 +
b11010110 =
15
b10100 :
1%
#2200000
0%
#2250000
b10 7
b10100 9
b10101 :
1%
#2300000
0%
#2350000
05
b1 2
b1011 3
b10101 <
b10110 :
1%
#2400000
0%
#2450000
b1100 >
b10011100 +
b10011100 =
15
b10111 :
1%
#2500000
0%
#2550000
05
b10 2
b1100 3
b11000 :
1%
#2600000
0%
#2650000
b1101 >
b10000101 +
b10000101 =
15
b11001 :
1%
#2700000
0%
#2750000
05
b11 2
b1101 3
b11010 :
1%
#2800000
0%
#2850000
b1110 >
b10001010 +
b10001010 =
15
b11011 :
1%
#2900000
0%
#2950000
05
b100 2
b1110 3
b11100 :
1%
#3000000
0%
#3050000
b1111 >
b10010001 +
b10010001 =
15
b11101 :
1%
#3100000
0%
#3150000
05
b101 2
b1111 3
b11110 :
1%
#3200000
0%
#3250000
b10000 >
b10001100 +
b10001100 =
15
b11111 :
1%
#3300000
0%
#3350000
05
b110 2
b10000 3
b100000 :
1%
#3400000
0%
#3450000
b10001 >
b10000001 +
b10000001 =
15
b100001 :
1%
#3500000
0%
#3550000
05
b111 2
b10001 3
b100010 :
1%
#3600000
0%
#3650000
b10010 >
b10001011 +
b10001011 =
15
b100011 :
1%
#3700000
0%
#3750000
05
b1000 2
b10010 3
b100100 :
1%
#3800000
0%
#3850000
b10011 >
b10011001 +
b10011001 =
15
b100101 :
1%
#3900000
0%
#3950000
05
b1001 2
b10011 3
b100110 :
1%
#4000000
0%
#4050000
b10100 >
b10011011 +
b10011011 =
15
b100111 :
1%
#4100000
0%
#4150000
05
b1010 2
b10100 3
b101000 :
1%
#4200000
0%
#4250000
b10101 >
b10010011 +
b10010011 =
15
b101001 :
1%
#4300000
0%
#4350000
05
b1011 2
b10101 3
b101010 :
1%
#4400000
0%
#4450000
b10110 >
b10000010 +
b10000010 =
15
b101011 :
1%
#4500000
0%
#4550000
05
b1100 2
b10110 3
b101100 :
1%
#4600000
0%
#4650000
b10111 >
b10010111 +
b10010111 =
15
b101101 :
1%
#4700000
0%
#4750000
05
b1101 2
b10111 3
b101110 :
1%
#4800000
0%
#4850000
b11000 >
b10010000 +
b10010000 =
15
b101111 :
1%
#4900000
0%
#4950000
05
b1110 2
b11000 3
b110000 :
1%
#5000000
0%
#5050000
b11001 >
b10011111 +
b10011111 =
15
b110001 :
1%
#5100000
0%
#5150000
05
b1111 2
b11001 3
b110010 :
1%
#5200000
0%
#5250000
b11010 >
b10100111 +
b10100111 =
15
b110011 :
1%
#5300000
0%
#5350000
05
b10000 2
b11010 3
b110100 :
1%
#5400000
0%
#5450000
b11011 >
b10001101 +
b10001101 =
15
b110101 :
1%
#5500000
0%
#5550000
b0 7
0;
1!
05
b10001 2
b11011 3
b110110 :
1%
#5600000
0%
#5650000
b0 )
0#
b1 "
b1 6
b11 7
1%
0'
#5700000
0%
#5750000
b1 4
b1 8
b10001011 "
b10001011 6
b1 )
1%
#5800000
0%
#5850000
b10 4
b10 8
b10001100 "
b10001100 6
b10 )
1%
#5900000
0%
#5950000
b11 4
b11 8
b10011001 "
b10011001 6
b11 )
1%
#6000000
0%
#6050000
b100 4
b100 8
b10011011 "
b10011011 6
b100 )
1%
#6100000
0%
#6150000
b101 4
b101 8
b10010011 "
b10010011 6
b101 )
1%
#6200000
0%
#6250000
b110 4
b110 8
b10000010 "
b10000010 6
b110 )
1%
#6300000
0%
#6350000
b111 4
b111 8
b10010111 "
b10010111 6
b111 )
1%
#6400000
0%
#6450000
b1000 4
b1000 8
b10010000 "
b10010000 6
b1000 )
1%
#6500000
0%
#6550000
b1001 4
b1001 8
b10011111 "
b10011111 6
b1001 )
1%
#6600000
0%
#6650000
b1010 4
b1010 8
b10010011 "
b10010011 6
b1010 )
1%
#6700000
0%
#6750000
b1011 4
b1011 8
b11010110 "
b11010110 6
b1011 )
1%
#6800000
0%
#6850000
b1100 4
b1100 8
b10011100 "
b10011100 6
b1100 )
1%
#6900000
0%
#6950000
b1101 4
b1101 8
b10000101 "
b10000101 6
b1101 )
1%
#7000000
0%
#7050000
b1110 4
b1110 8
b10001010 "
b10001010 6
b1110 )
1%
#7100000
0%
#7150000
b1111 4
b1111 8
b10010001 "
b10010001 6
b1111 )
1%
#7200000
0%
#7250000
b10000 4
b10000 8
b10001100 "
b10001100 6
b10000 )
1%
#7300000
0%
#7350000
b10001 4
b10001 8
b10000001 "
b10000001 6
b10001 )
1%
#7400000
0%
#7450000
b10010 4
b10010 8
b10001011 "
b10001011 6
b10010 )
1%
#7500000
0%
#7550000
b10011 4
b10011 8
b10011001 "
b10011001 6
b10011 )
1%
#7600000
0%
#7650000
b10100 4
b10100 8
b10011011 "
b10011011 6
b10100 )
1%
#7700000
0%
#7750000
b10101 4
b10101 8
b10010011 "
b10010011 6
b10101 )
1%
#7800000
0%
#7850000
b10110 4
b10110 8
b10000010 "
b10000010 6
b10110 )
1%
#7900000
0%
#7950000
b10111 4
b10111 8
b10010111 "
b10010111 6
b10111 )
1%
#8000000
0%
#8050000
b11000 4
b11000 8
b10010000 "
b10010000 6
b11000 )
1%
#8100000
0%
#8150000
b11001 4
b11001 8
b10011111 "
b10011111 6
b11001 )
1%
#8200000
0%
#8250000
b11010 4
b11010 8
b10100111 "
b10100111 6
b11010 )
1%
#8300000
0%
#8350000
b11011 4
b11011 8
b10001101 "
b10001101 6
b11011 )
1%
#8400000
0%
#8450000
b11100 4
b11100 8
b0xxxxxxxx "
b0xxxxxxxx 6
b11100 )
1%
#8500000
0%
#8550000
b11101 4
b11101 8
b11101 )
1%
#8600000
0%
#8650000
b11110 4
b11110 8
b11110 )
1%
#8700000
0%
#8750000
b11111 4
b11111 8
b11111 )
1%
#8800000
0%
#8850000
b100000 4
b0 8
b100000 )
1%
#8900000
0%
#8950000
b0 7
1#
b0 "
b0 6
0!
1%
